odoo/addons/l10n_es_pos_by_device/README.rst
odoo/addons/l10n_es_pos_by_device/__init__.py
odoo/addons/l10n_es_pos_by_device/__manifest__.py
odoo/addons/l10n_es_pos_by_device/i18n/es.po
odoo/addons/l10n_es_pos_by_device/i18n/l10n_es_pos_by_device.pot
odoo/addons/l10n_es_pos_by_device/models/__init__.py
odoo/addons/l10n_es_pos_by_device/models/pos_config.py
odoo/addons/l10n_es_pos_by_device/models/pos_device.py
odoo/addons/l10n_es_pos_by_device/models/pos_order.py
odoo/addons/l10n_es_pos_by_device/models/res_company.py
odoo/addons/l10n_es_pos_by_device/models/res_config_settings.py
odoo/addons/l10n_es_pos_by_device/readme/CONFIGURE.rst
odoo/addons/l10n_es_pos_by_device/readme/CONTRIBUTORS.rst
odoo/addons/l10n_es_pos_by_device/readme/DESCRIPTION.rst
odoo/addons/l10n_es_pos_by_device/readme/USAGE.rst
odoo/addons/l10n_es_pos_by_device/security/device_security.xml
odoo/addons/l10n_es_pos_by_device/security/ir.model.access.csv
odoo/addons/l10n_es_pos_by_device/static/description/icon.png
odoo/addons/l10n_es_pos_by_device/static/description/index.html
odoo/addons/l10n_es_pos_by_device/static/src/js/PaymentScreen.js
odoo/addons/l10n_es_pos_by_device/static/src/js/models.js
odoo/addons/l10n_es_pos_by_device/static/src/js/Screens/Chrome/Chrome.js
odoo/addons/l10n_es_pos_by_device/static/src/js/Screens/Chrome/DeviceName.js
odoo/addons/l10n_es_pos_by_device/static/src/xml/Screens/Chrome/Chrome.xml
odoo/addons/l10n_es_pos_by_device/static/src/xml/Screens/Chrome/DeviceName.xml
odoo/addons/l10n_es_pos_by_device/views/pos_templates.xml
odoo/addons/l10n_es_pos_by_device/views/pos_views.xml
odoo/addons/l10n_es_pos_by_device/views/res_config_views.xml
odoo14_addon_l10n_es_pos_by_device-14.0.1.1.1.dist-info/METADATA
odoo14_addon_l10n_es_pos_by_device-14.0.1.1.1.dist-info/WHEEL
odoo14_addon_l10n_es_pos_by_device-14.0.1.1.1.dist-info/top_level.txt
odoo14_addon_l10n_es_pos_by_device-14.0.1.1.1.dist-info/RECORD
