Metadata-Version: 2.1
Name: odoo14-addon-l10n-es-pos-by-device
Version: 14.0.1.1.1
Summary: Punto de venta adaptado a la legislación española por dispositivo
Home-page: https://github.com/OCA/l10n-spain
Author: Landoo Sistemas de Información S.L, Odoo Community Association (OCA)
Author-email: support@odoo-community.org
License: AGPL-3
Platform: UNKNOWN
Classifier: Programming Language :: Python
Classifier: Framework :: Odoo
Classifier: Framework :: Odoo :: 14.0
Classifier: License :: OSI Approved :: GNU Affero General Public License v3
Requires-Python: >=3.6
Requires-Dist: odoo14-addon-l10n-es-pos
Requires-Dist: odoo (<14.1dev,>=14.0a)
